ovos_wolfram_alpha_solver/__init__.py
ovos_wolfram_alpha_solver/version.py
ovos_wolfram_alpha_solver-0.0.4.dist-info/METADATA
ovos_wolfram_alpha_solver-0.0.4.dist-info/WHEEL
ovos_wolfram_alpha_solver-0.0.4.dist-info/entry_points.txt
ovos_wolfram_alpha_solver-0.0.4.dist-info/top_level.txt
ovos_wolfram_alpha_solver-0.0.4.dist-info/RECORD
