Metadata-Version: 2.4
Name: ovos_wolfram_alpha_solver
Version: 0.0.4
Summary: ovos wolfram-alpha plugin
Home-page: https://github.com/OpenVoiceOS/ovos-wolfram-alpha-solver
Author: JarbasAi
Author-email: jarbasai@mailfence.com
License: Apache-2.0
Keywords: ovos skill plugin
Requires-Dist: ovos-utils<1.0.0,>=0.7.0
Requires-Dist: ovos-plugin-manager<3.0.0,>=0.0.26
Dynamic: author
Dynamic: author-email
Dynamic: description
Dynamic: description-content-type
Dynamic: home-page
Dynamic: keywords
Dynamic: license
Dynamic: requires-dist
Dynamic: summary
